Metadata-Version: 2.4
Name: d3tales_api
Version: 0.2.0
Summary: API for parsing, database connection, and property calculations for D3taLES project 
Home-page: https://github.com/D3TaLES/d3tales_api
Author: Rebekah Duke
Author-email: d3tales@gmail.com
License: MIT
Project-URL: Bug Tracker, https://github.com/D3TaLES/d3tales_api/issues
License-File: LICENSE
Requires-Dist: articledownloader>=9.1.1
Requires-Dist: atomate>=1.0.3
Requires-Dist: autologging>=1.3.2
Requires-Dist: cclib>=1.7.2
Requires-Dist: dbstep>=1.0.0
Requires-Dist: Django>=2.2.28
Requires-Dist: dotty_dict>=1.3.1
Requires-Dist: elsapy>=0.5.1
Requires-Dist: FireWorks>=2.0.3
Requires-Dist: inflection>=0.5.1
Requires-Dist: interruptingcow>=0.8
Requires-Dist: jsonschema>=3.2.0
Requires-Dist: matplotlib>=3.1.3
Requires-Dist: monty>=2022.9.9
Requires-Dist: nanoid>=2.0.0
Requires-Dist: numpy>=1.23.5
Requires-Dist: pandas>=1.5.1
Requires-Dist: paramiko>=3.0.0
Requires-Dist: Pillow>=9.3.0
Requires-Dist: Pint>=0.20.1
Requires-Dist: PubChemPy>=1.0.4
Requires-Dist: pymongo>=3.12.3
Requires-Dist: python-dateutil>=2.8.2
Requires-Dist: python_jsonschema_objects>=0.4.1
Requires-Dist: rdkit>=2022.9.1
Requires-Dist: requests>=2.28.1
Requires-Dist: scipy>=1.8.0
Requires-Dist: seaborn>=0.12.1
Requires-Dist: selfies>=2.1.1
Requires-Dist: setuptools>=60.2.0
Requires-Dist: tqdm>=4.64.1
Dynamic: author
Dynamic: author-email
Dynamic: description
Dynamic: description-content-type
Dynamic: home-page
Dynamic: license
Dynamic: license-file
Dynamic: project-url
Dynamic: requires-dist
Dynamic: summary
